pandorasim/__init__.py
pandorasim/docstrings.py
pandorasim/nirsim.py
pandorasim/sim.py
pandorasim/utils.py
pandorasim/visiblesim.py
pandorasim-1.2.0.dist-info/METADATA
pandorasim-1.2.0.dist-info/WHEEL
pandorasim-1.2.0.dist-info/licenses/LICENSE
pandorasim-1.2.0.dist-info/RECORD
